Workbook

Sheet 📊 Sales Report
A1: 📊 DAILY SALES REPORT
A4: Date | B4: Invoice # | C4: Product Name | D4: Category | E4: Qty Sold | F4: Unit Price | G4: Discount (%) | H4: Tax (%) | I4: Total Amount | J4: Payment Method | K4: Cashier | L4: Customer Name | M4: Profit/Item | N4: Total Profit
I5: =E5*F5*(1-G5/100)*(1+H5/100) | M5: =F5*(1-G5/100)-2.8 | N5: =M5*E5
I6: =E6*F6*(1-G6/100)*(1+H6/100) | M6: =F6*(1-G6/100)-2.8 | N6: =M6*E6
I7: =E7*F7*(1-G7/100)*(1+H7/100) | M7: =F7*(1-G7/100)-2.8 | N7: =M7*E7
I8: =E8*F8*(1-G8/100)*(1+H8/100) | M8: =F8*(1-G8/100)-2.8 | N8: =M8*E8
I9: =E9*F9*(1-G9/100)*(1+H9/100) | M9: =F9*(1-G9/100)-2.8 | N9: =M9*E9
I10: =E10*F10*(1-G10/100)*(1+H10/100) | M10: =F10*(1-G10/100)-2.8 | N10: =M10*E10
I11: =E11*F11*(1-G11/100)*(1+H11/100) | M11: =F11*(1-G11/100)-2.8 | N11: =M11*E11
I12: =E12*F12*(1-G12/100)*(1+H12/100) | M12: =F12*(1-G12/100)-2.8 | N12: =M12*E12
I13: =E13*F13*(1-G13/100)*(1+H13/100) | M13: =F13*(1-G13/100)-2.8 | N13: =M13*E13
I14: =E14*F14*(1-G14/100)*(1+H14/100) | M14: =F14*(1-G14/100)-2.8 | N14: =M14*E14
I15: =E15*F15*(1-G15/100)*(1+H15/100) | M15: =F15*(1-G15/100)-2.8 | N15: =M15*E15
I16: =E16*F16*(1-G16/100)*(1+H16/100) | M16: =F16*(1-G16/100)-2.8 | N16: =M16*E16
... I504: =E504*F504*(1-G504/100)*(1+H504/100) | M504: =F504*(1-G504/100)-2.8 | N504: =M504*E504

Sheet 📦 Inventory
A1: 📦 PRODUCT INVENTORY MANAGEMENT
A4: Product ID | B4: Barcode | C4: Product Name | D4: Category | E4: Supplier | F4: Cost Price | G4: Selling Price | H4: Current Stock | I4: Min Stock Level | J4: Stock Status | K4: Inventory Value | L4: Expiry Date
J5: =IF(H5=0,"OUT OF STOCK",IF(H5<=I5,"LOW STOCK","In Stock")) | K5: =H5*G5
J6: =IF(H6=0,"OUT OF STOCK",IF(H6<=I6,"LOW STOCK","In Stock")) | K6: =H6*G6
J7: =IF(H7=0,"OUT OF STOCK",IF(H7<=I7,"LOW STOCK","In Stock")) | K7: =H7*G7
J8: =IF(H8=0,"OUT OF STOCK",IF(H8<=I8,"LOW STOCK","In Stock")) | K8: =H8*G8
J9: =IF(H9=0,"OUT OF STOCK",IF(H9<=I9,"LOW STOCK","In Stock")) | K9: =H9*G9
J10: =IF(H10=0,"OUT OF STOCK",IF(H10<=I10,"LOW STOCK","In Stock")) | K10: =H10*G10
J11: =IF(H11=0,"OUT OF STOCK",IF(H11<=I11,"LOW STOCK","In Stock")) | K11: =H11*G11
J12: =IF(H12=0,"OUT OF STOCK",IF(H12<=I12,"LOW STOCK","In Stock")) | K12: =H12*G12
J13: =IF(H13=0,"OUT OF STOCK",IF(H13<=I13,"LOW STOCK","In Stock")) | K13: =H13*G13
J14: =IF(H14=0,"OUT OF STOCK",IF(H14<=I14,"LOW STOCK","In Stock")) | K14: =H14*G14
J15: =IF(H15=0,"OUT OF STOCK",IF(H15<=I15,"LOW STOCK","In Stock")) | K15: =H15*G15
J16: =IF(H16=0,"OUT OF STOCK",IF(H16<=I16,"LOW STOCK","In Stock")) | K16: =H16*G16
... J204: =IF(H204=0,"OUT OF STOCK",IF(H204<=I204,"LOW STOCK","In Stock")) | K204: =H204*G204

Sheet 💸 Expenses
A1: 💸 EXPENSE TRACKING SHEET
A4: Date | B4: Expense Category | C4: Description | D4: Supplier/Vendor | E4: Payment Method | F4: Amount | G4: Approved By

Sheet 👥 Payroll
A1: 👥 PAYROLL & SALARY CALCULATION
A4: Emp ID | B4: Employee Name | C4: Position | D4: Daily Rate | E4: Attendance Days | F4: Hours Worked | G4: OT Hours | H4: OT Pay | I4: Gross Salary | J4: SSS | K4: PhilHealth | L4: Pag-IBIG | M4: Late Penalty | N4: Net Salary
H5: =ROUND((D5/8)*1.25*G5,2) | I5: =D5*E5+H5 | N5: =I5-J5-K5-L5-M5
H6: =ROUND((D6/8)*1.25*G6,2) | I6: =D6*E6+H6 | N6: =I6-J6-K6-L6-M6
H7: =ROUND((D7/8)*1.25*G7,2) | I7: =D7*E7+H7 | N7: =I7-J7-K7-L7-M7
H8: =ROUND((D8/8)*1.25*G8,2) | I8: =D8*E8+H8 | N8: =I8-J8-K8-L8-M8
H9: =ROUND((D9/8)*1.25*G9,2) | I9: =D9*E9+H9 | N9: =I9-J9-K9-L9-M9
H10: =ROUND((D10/8)*1.25*G10,2) | I10: =D10*E10+H10 | N10: =I10-J10-K10-L10-M10
H11: =ROUND((D11/8)*1.25*G11,2) | I11: =D11*E11+H11 | N11: =I11-J11-K11-L11-M11
H12: =ROUND((D12/8)*1.25*G12,2) | I12: =D12*E12+H12 | N12: =I12-J12-K12-L12-M12
H13: =ROUND((D13/8)*1.25*G13,2) | I13: =D13*E13+H13 | N13: =I13-J13-K13-L13-M13
H14: =ROUND((D14/8)*1.25*G14,2) | I14: =D14*E14+H14 | N14: =I14-J14-K14-L14-M14
H15: =ROUND((D15/8)*1.25*G15,2) | I15: =D15*E15+H15 | N15: =I15-J15-K15-L15-M15
H16: =ROUND((D16/8)*1.25*G16,2) | I16: =D16*E16+H16 | N16: =I16-J16-K16-L16-M16
... H104: =ROUND((D104/8)*1.25*G104,2) | I104: =D104*E104+H104 | N104: =I104-J104-K104-L104-M104

Sheet 🏆 Performance
A1: 🏆 EMPLOYEE PERFORMANCE TRACKER
A4: Employee Name | B4: Total Sales | C4: Transactions | D4: Avg Sale | E4: Attendance % | F4: Customer Rating | G4: Performance Score | H4: Rank
B5: =SUMIF('📊 Sales Report'!K$5:K$504,A5,'📊 Sales Report'!I$5:I$504) | C5: =COUNTIF('📊 Sales Report'!K$5:K$504,A5) | D5: =IFERROR(B5/C5,0) | G5: =ROUND((B5/MAX($B$5:$B$54)*40)+(C5/MAX($C$5:$C$54)*30)+(F5/5*30),1) | H5: =RANK(G5,$G$5:$G$54,0)
B6: =SUMIF('📊 Sales Report'!K$5:K$504,A6,'📊 Sales Report'!I$5:I$504) | C6: =COUNTIF('📊 Sales Report'!K$5:K$504,A6) | D6: =IFERROR(B6/C6,0) | G6: =ROUND((B6/MAX($B$5:$B$54)*40)+(C6/MAX($C$5:$C$54)*30)+(F6/5*30),1) | H6: =RANK(G6,$G$5:$G$54,0)
B7: =SUMIF('📊 Sales Report'!K$5:K$504,A7,'📊 Sales Report'!I$5:I$504) | C7: =COUNTIF('📊 Sales Report'!K$5:K$504,A7) | D7: =IFERROR(B7/C7,0) | G7: =ROUND((B7/MAX($B$5:$B$54)*40)+(C7/MAX($C$5:$C$54)*30)+(F7/5*30),1) | H7: =RANK(G7,$G$5:$G$54,0)
B8: =SUMIF('📊 Sales Report'!K$5:K$504,A8,'📊 Sales Report'!I$5:I$504) | C8: =COUNTIF('📊 Sales Report'!K$5:K$504,A8) | D8: =IFERROR(B8/C8,0) | G8: =ROUND((B8/MAX($B$5:$B$54)*40)+(C8/MAX($C$5:$C$54)*30)+(F8/5*30),1) | H8: =RANK(G8,$G$5:$G$54,0)
B9: =SUMIF('📊 Sales Report'!K$5:K$504,A9,'📊 Sales Report'!I$5:I$504) | C9: =COUNTIF('📊 Sales Report'!K$5:K$504,A9) | D9: =IFERROR(B9/C9,0) | G9: =ROUND((B9/MAX($B$5:$B$54)*40)+(C9/MAX($C$5:$C$54)*30)+(F9/5*30),1) | H9: =RANK(G9,$G$5:$G$54,0)
B10: =SUMIF('📊 Sales Report'!K$5:K$504,A10,'📊 Sales Report'!I$5:I$504) | C10: =COUNTIF('📊 Sales Report'!K$5:K$504,A10) | D10: =IFERROR(B10/C10,0) | G10: =ROUND((B10/MAX($B$5:$B$54)*40)+(C10/MAX($C$5:$C$54)*30)+(F10/5*30),1) | H10: =RANK(G10,$G$5:$G$54,0)
B11: =SUMIF('📊 Sales Report'!K$5:K$504,A11,'📊 Sales Report'!I$5:I$504) | C11: =COUNTIF('📊 Sales Report'!K$5:K$504,A11) | D11: =IFERROR(B11/C11,0) | G11: =ROUND((B11/MAX($B$5:$B$54)*40)+(C11/MAX($C$5:$C$54)*30)+(F11/5*30),1) | H11: =RANK(G11,$G$5:$G$54,0)
B12: =SUMIF('📊 Sales Report'!K$5:K$504,A12,'📊 Sales Report'!I$5:I$504) | C12: =COUNTIF('📊 Sales Report'!K$5:K$504,A12) | D12: =IFERROR(B12/C12,0) | G12: =ROUND((B12/MAX($B$5:$B$54)*40)+(C12/MAX($C$5:$C$54)*30)+(F12/5*30),1) | H12: =RANK(G12,$G$5:$G$54,0)
B13: =SUMIF('📊 Sales Report'!K$5:K$504,A13,'📊 Sales Report'!I$5:I$504) | C13: =COUNTIF('📊 Sales Report'!K$5:K$504,A13) | D13: =IFERROR(B13/C13,0) | G13: =ROUND((B13/MAX($B$5:$B$54)*40)+(C13/MAX($C$5:$C$54)*30)+(F13/5*30),1) | H13: =RANK(G13,$G$5:$G$54,0)
B14: =SUMIF('📊 Sales Report'!K$5:K$504,A14,'📊 Sales Report'!I$5:I$504) | C14: =COUNTIF('📊 Sales Report'!K$5:K$504,A14) | D14: =IFERROR(B14/C14,0) | G14: =ROUND((B14/MAX($B$5:$B$54)*40)+(C14/MAX($C$5:$C$54)*30)+(F14/5*30),1) | H14: =RANK(G14,$G$5:$G$54,0)
B15: =SUMIF('📊 Sales Report'!K$5:K$504,A15,'📊 Sales Report'!I$5:I$504) | C15: =COUNTIF('📊 Sales Report'!K$5:K$504,A15) | D15: =IFERROR(B15/C15,0) | G15: =ROUND((B15/MAX($B$5:$B$54)*40)+(C15/MAX($C$5:$C$54)*30)+(F15/5*30),1) | H15: =RANK(G15,$G$5:$G$54,0)
B16: =SUMIF('📊 Sales Report'!K$5:K$504,A16,'📊 Sales Report'!I$5:I$504) | C16: =COUNTIF('📊 Sales Report'!K$5:K$504,A16) | D16: =IFERROR(B16/C16,0) | G16: =ROUND((B16/MAX($B$5:$B$54)*40)+(C16/MAX($C$5:$C$54)*30)+(F16/5*30),1) | H16: =RANK(G16,$G$5:$G$54,0)
... B54: =SUMIF('📊 Sales Report'!K$5:K$504,A54,'📊 Sales Report'!I$5:I$504) | C54: =COUNTIF('📊 Sales Report'!K$5:K$504,A54) | D54: =IFERROR(B54/C54,0) | G54: =ROUND((B54/MAX($B$5:$B$54)*40)+(C54/MAX($C$5:$C$54)*30)+(F54/5*30),1) | H54: =RANK(G54,$G$5:$G$54,0)

Sheet 🚚 Suppliers
A1: 🚚 SUPPLIER & PURCHASE RECORDS
A4: Purchase Date | B4: Supplier Name | C4: Product Purchased | D4: Quantity | E4: Unit Cost | F4: Total Amount | G4: Delivery Status | H4: Payment Status
F5: =D5*E5
F6: =D6*E6
F7: =D7*E7
F8: =D8*E8
F9: =D9*E9
F10: =D10*E10
F11: =D11*E11
F12: =D12*E12
F13: =D13*E13
F14: =D14*E14
F15: =D15*E15
F16: =D16*E16
... F204: =D204*E204

Sheet 💰 Cash Flow
A1: 💰 DAILY CASH FLOW REGISTER
A4: Date | B4: Opening Balance | C4: Cash In (Sales) | D4: Cash Out (Expenses) | E4: Bank Deposit | F4: Withdrawal | G4: Petty Cash | H4: Closing Balance
H5: =B5+C5-D5-E5+F5-G5
H6: =B6+C6-D6-E6+F6-G6
H7: =B7+C7-D7-E7+F7-G7
H8: =B8+C8-D8-E8+F8-G8
H9: =B9+C9-D9-E9+F9-G9
H10: =B10+C10-D10-E10+F10-G10
H11: =B11+C11-D11-E11+F11-G11
H12: =B12+C12-D12-E12+F12-G12
H13: =B13+C13-D13-E13+F13-G13
H14: =B14+C14-D14-E14+F14-G14
H15: =B15+C15-D15-E15+F15-G15
H16: =B16+C16-D16-E16+F16-G16
... H204: =B204+C204-D204-E204+F204-G204

Sheet ⚙ Settings
A1: ⚙ BUSINESS SETTINGS & CONFIGURATION
A4: BUSINESS INFORMATION
B5: Business Name | C5: My Retail Store | D5: ← Edit this value
B6: Address | C6: 123 Main Street, City | D6: ← Edit this value
B7: Phone | C7: +63 900 000 0000 | D7: ← Edit this value
B8: Email | C8: info@mystore.com | D8: ← Edit this value
B9: Tax / Business ID | C9: TIN-000-000-000 | D9: ← Edit this value
B10: Currency Symbol | C10: ₱ | D10: ← Edit this value
A11: FINANCIAL SETTINGS
B12: VAT Rate (%) | C12: 12 | D12: ← Edit this value
B13: Overtime Multiplier | C13: 1.25 | D13: ← Edit this value
B14: Late Penalty/Minute | C14: 2 | D14: ← Edit this value
B15: SSS Deduction | C15: 500 | D15: ← Edit this value
B16: PhilHealth Deduction | C16: 250 | D16: ← Edit this value
B17: Pag-IBIG Deduction | C17: 100 | D17: ← Edit this value
A18: REPORT SETTINGS
B19: Report Start Date | C19: 45658 | D19: ← Edit this value
B20: Report End Date | C20: 46022 | D20: ← Edit this value
B21: Fiscal Year | C21: 2025 | D21: ← Edit this value
B22: Low Stock Threshold | C22: 10 | D22: ← Edit this value
B23: Expiry Warning Days | C23: 30 | D23: ← Edit this value
